csvchk/__init__.py
csvchk/csvchk.py
csvchk/tests/csvchk_test.py
csvchk-0.3.2.dist-info/LICENSE
csvchk-0.3.2.dist-info/METADATA
csvchk-0.3.2.dist-info/WHEEL
csvchk-0.3.2.dist-info/top_level.txt
csvchk-0.3.2.dist-info/RECORD
