Metadata-Version: 2.1
Name: csvchk
Version: 0.3.2
Summary: Vertical display of delimited data
Author-email: Ken Youens-Clark <kyclark@gmail.com>
Project-URL: Homepage, https://github.com/kyclark/csvchk
Project-URL: Bug Tracker, https://github.com/kyclark/csvchk/issues
Classifier: Programming Language :: Python :: 3
Classifier: License :: OSI Approved :: MIT License
Classifier: Operating System :: OS Independent
Requires-Python: >=3.7
License-File: LICENSE
